__init__.py
add_concept_tool.py
carton_utils.py
concept_config.py
wiki_config.py
carton_mcp-0.1.37.dist-info/METADATA
carton_mcp-0.1.37.dist-info/WHEEL
carton_mcp-0.1.37.dist-info/RECORD
