Metadata-Version: 2.4
Name: carton-mcp
Version: 0.1.37
Summary: CartOn - Cartographic knowledge graph mapping for concept networks
Author: HEAVEN System
Requires-Python: >=3.11
Requires-Dist: gitpython>=3.1.0
Requires-Dist: heaven-framework>=0.1.14
Requires-Dist: mcp>=1.0.0
Requires-Dist: neo4j>=5.0.0
